<?xml version="1.0" encoding="UTF-8"?>
<!DOCTYPE mapper PUBLIC "-//mybatis.org//DTD Mapper 3.0//EN" "http://mybatis.org/dtd/mybatis-3-mapper.dtd">
<mapper namespace="com.zhangz.security.mapper.ProductExtMapper">
  <resultMap id="BaseResultMap" type="com.zhangz.security.model.Product">
    <!--
      WARNING - @mbg.generated
      This element is automatically generated by MyBatis Generator, do not modify.
      This element was generated on Sat Mar 07 16:19:21 CST 2020.
    -->
    <id column="product_id" jdbcType="BIGINT" property="productId" />
    <result column="site_id" jdbcType="BIGINT" property="siteId" />
    <result column="batch_id" jdbcType="BIGINT" property="batchId" />
    <result column="item_id" jdbcType="BIGINT" property="itemId" />
    <result column="vendor" jdbcType="BIGINT" property="vendor" />
    <result column="product_name" jdbcType="VARCHAR" property="productName" />
    <result column="description" jdbcType="VARCHAR" property="description" />
    <result column="composition" jdbcType="VARCHAR" property="composition" />
    <result column="is_delete" jdbcType="INTEGER" property="isDelete" />
    <result column="site_name" jdbcType="VARCHAR" property="siteName" />
    <result column="item_name" jdbcType="VARCHAR" property="itemName" />
    <result column="vendor_name" jdbcType="VARCHAR" property="vendorName" />
  </resultMap>
  <!--customized-->


  <insert id="batchInsert" parameterType="com.zhangz.security.model.Product">
    INSERT INTO product
    (product_id, site_id, batch_id, item_id, vendor, product_name, description, composition, is_delete, site_name, item_name, vendor_name)
    VALUES
    <foreach collection="list" item="product" separator=",">
      ( #{product.productId}, #{product.siteId}, #{product.batchId}, #{product.itemId}, #{product.vendor}, #{product.productName}, #{product.description}, #{product.composition}, #{product.isDelete}, #{product.siteName}, #{product.itemName}, #{product.vendorName})
    </foreach>
  </insert>
</mapper>